enumerate_all_files_in_folder/LICENSE
enumerate_all_files_in_folder/README.MD
enumerate_all_files_in_folder/__init__.py
enumerate_all_files_in_folder/requirements.txt
enumerate_all_files_in_folder/thirdparty.json
enumerate_all_files_in_folder-0.10.dist-info/LICENSE.rst
enumerate_all_files_in_folder-0.10.dist-info/METADATA
enumerate_all_files_in_folder-0.10.dist-info/WHEEL
enumerate_all_files_in_folder-0.10.dist-info/top_level.txt
enumerate_all_files_in_folder-0.10.dist-info/RECORD
