Metadata-Version: 2.1
Name: enumerate-all-files-in-folder
Version: 0.10
Summary: A function that enumerates all files in a folder (and subfolders)
Home-page: https://github.com/hansalemaos/enumerate_all_files_in_folder
Author: Johannes Fischer
Author-email: <aulasparticularesdealemaosp@gmail.com>
License: MIT
Keywords: folder,files,sort
Classifier: Development Status :: 4 - Beta
Classifier: Programming Language :: Python :: 3 :: Only
Classifier: Programming Language :: Python :: 3.9
Classifier: Topic :: Scientific/Engineering :: Visualization
Classifier: Topic :: Software Development :: Libraries :: Python Modules
Classifier: Topic :: Text Editors :: Text Processing
Classifier: Topic :: Text Processing :: General
Classifier: Topic :: Text Processing :: Indexing
Classifier: Topic :: Text Processing :: Filters
Classifier: Topic :: Utilities
License-File: LICENSE.rst
Requires-Dist: FastCopyFast
Requires-Dist: flatten-everything
Requires-Dist: more-itertools
Requires-Dist: touchtouch
